datamanipy/__init__.py
datamanipy/database.py
datamanipy/database_info.py
datamanipy/file.py
datamanipy-1.2.4.dist-info/LICENSE
datamanipy-1.2.4.dist-info/METADATA
datamanipy-1.2.4.dist-info/WHEEL
datamanipy-1.2.4.dist-info/top_level.txt
datamanipy-1.2.4.dist-info/RECORD
