Metadata-Version: 2.1
Name: datamanipy
Version: 1.2.4
Summary: A Python package that provides tools to help you manipulating data.
Author: Alexandre Le Potier
Classifier: Programming Language :: Python :: 3
Classifier: License :: OSI Approved :: MIT License
Classifier: Operating System :: OS Independent
Requires-Python: >=3.9
License-File: LICENSE
Requires-Dist: sqlalchemy (>=1.4.28)
Requires-Dist: pandas (>=1.3.5)
Requires-Dist: keyring (>=23.5.0)
Requires-Dist: pyreadstat (>=1.1.4)
Requires-Dist: openpyxl (>=3.0.10)
Requires-Dist: datetime (>=4.3)
